{
    "sections": [
        {
            "IMAGE": [
                "https://s100.divarcdn.com/static/photo/neda/post/a86vfQ_7RltPc5M1KhlzXQ/c03868d1-c552-42cb-a3e1-2a2ac9cae112.jpg",
                "https://s100.divarcdn.com/static/photo/neda/post/yoUHpxQ-a0xkPaB6aM6ukQ/bed8962b-c195-4caa-9777-8cf38e6dfdcb.jpg",
                "https://s100.divarcdn.com/static/photo/neda/post/74jia668BWUWA6KfvgLGnQ/59ed81ec-d1ed-41ce-b91f-4c0d74d20787.jpg",
                "https://s100.divarcdn.com/static/photo/neda/post/VgCpUOUYq9xOmcsbqwK2Rw/757a9190-abc7-4051-9e55-9312df800224.jpg",
                "https://s100.divarcdn.com/static/photo/neda/post/DHcLHWPYoECSu8VO-es1Gg/55be8203-9717-402b-b946-58351668a21b.jpg",
                "https://s100.divarcdn.com/static/photo/neda/post/nbdg-_rsfaDLAKGOQxcZHg/a099835f-8986-40f6-afc6-d9ead7ca5f84.jpg",
                "https://s100.divarcdn.com/static/photo/neda/post/1XMY3Rme91WM5PtnsnGYrQ/de3211c3-4de6-4bfb-8135-20f892acbacd.jpg"
            ]
        },
        {
            "LIST_DATA": {
                "Property": [
                    {
                        "title": "متراژ",
                        "value": "۱۲۰"
                    },
                    {
                        "title": "اتاق",
                        "value": "۱"
                    }
                ]
            }
        }
    ],
    "seo": {
        "title": "اجاره سوییت درغارعلیصدر در همدان",
        "description": "آگهی اجاره سوییت درغارعلیصدر در دیوار همدان",
        "web_info": {
            "title": "اجاره سوییت درغارعلیصدر",
            "city_persian": "همدان",
            "category_slug_persian": "اجارهٔ کوتاه مدت آپارتمان و سوئیت"
        },
        "register_date": "09-9-2024"
    },
    "category": {
        "cat1": "real-estate",
        "cat2": "temporary-rent",
        "cat3": "suite-apartment",
        "city": "hamedan"
    },
    "details": {
        "business_ref": "",
        "business_type": "personal",
        "category": "suite-apartment",
        "city": "hamedan",
        "credit": 0,
        "district": "",
        "image_count": 7,
        "price": 0,
        "rent": 0,
        "token": "gZdvYuvq"
    }
}