{
    "sections": [
        {
            "IMAGE": [
                "https://s100.divarcdn.com/static/photo/afra/post/3L-2L1IT7bjC0s2aFcwTvg/21341233-d448-45ed-b701-aeba3d59434c.jpg",
                "https://s100.divarcdn.com/static/photo/afra/post/6fl-RDS9vXuo1SLOr0wthA/d52a21fe-ca71-439f-a940-8cccb3c18164.jpg",
                "https://s100.divarcdn.com/static/photo/afra/post/Xlb-O5qVV_g8SB1zqPEtEw/eb3b2816-19f9-4a91-a770-9c04ba4bd668.jpg",
                "https://s100.divarcdn.com/static/photo/afra/post/iR_tReW-TTj_1PmpeVrUbg/b01f3e14-d9b2-4641-b35c-810e99a69418.jpg",
                "https://s100.divarcdn.com/static/photo/afra/post/yeZdnooPbCDZsQ94TmOqBQ/b0b395c8-d86c-48f1-ae19-9cc9b8f2fa2d.jpg",
                "https://s100.divarcdn.com/static/photo/afra/post/3Oe5nS50zZah0lYw9G8bGQ/398b678b-ce26-4168-8cc1-8e58b05b2a33.jpg",
                "https://s100.divarcdn.com/static/photo/afra/post/E6u8b6hHx1MrCin7ZC8wtQ/db0d691e-47f1-4b75-af55-0bcaf4e7a254.jpg"
            ]
        },
        {
            "MAP": {
                "exact_data": {
                    "point": {
                        "latitude": 35.72276,
                        "longitude": 51.756855
                    }
                }
            }
        },
        {
            "section_name": "BUSINESS_SECTION",
            "widgets": [
                {
                    "widget_type": "LAZY_SECTION",
                    "data": {
                        "rest_request_path": "/v8/premium-user/post-page/business-data/gZmjfwwY/lazy",
                        "grpc_request_path": "/premium_panel.PremiumPanel/GetPostBusinessLazyWidgets",
                        "request_data": {
                            "@type": "type.googleapis.com/premium_panel.GetPostBusinessLazyWidgetsRequest.RequestData",
                            "post_token": "gZmjfwwY"
                        }
                    }
                }
            ]
        },
        {
            "LIST_DATA": {
                "Property": [
                    {
                        "title": "متراژ",
                        "value": "۱۰۵"
                    },
                    {
                        "title": "ساخت",
                        "value": "۱۴۰۲"
                    },
                    {
                        "title": "اتاق",
                        "value": "۲"
                    },
                    {
                        "title": "تعداد واحد در طبقه",
                        "value": "۲"
                    },
                    {
                        "title": "سند",
                        "value": "سایر"
                    },
                    {
                        "title": "جهت ساختمان",
                        "value": "شرقی"
                    },
                    {
                        "title": "وضعیت واحد",
                        "value": "بازسازی شده"
                    }
                ],
                "benefit": [
                    "آسانسور",
                    "پارکینگ",
                    "انباری",
                    "بالکن ",
                    "جنس کف پارکت لمینت",
                    "سرویس بهداشتی ایرانی و فرنگی",
                    "سرمایش کولر آبی",
                    "گرمایش شوفاژ",
                    "تأمین‌کننده آب گرم پکیج"
                ]
            }
        }
    ],
    "seo": {
        "title": "فروش آپارتمان پردیس فاز۸_پروژه نگین سازه در پردیس - ۲۷ شهریور ۱۴۰۳",
        "description": "آگهی فروش آپارتمان پردیس فاز۸_پروژه نگین سازه در دیوار پردیس",
        "web_info": {
            "title": "فروش آپارتمان پردیس فاز۸_پروژه نگین سازه",
            "city_persian": "پردیس",
            "category_slug_persian": "فروش آپارتمان"
        },
        "register_date": "16-9-2024"
    },
    "category": {
        "cat1": "real-estate",
        "cat2": "residential-sell",
        "cat3": "apartment-sell",
        "city": "pardis-city"
    },
    "details": {
        "business_ref": "fbZouBMA_JAmsvIKf",
        "business_type": "premium-panel",
        "category": "apartment-sell",
        "city": "pardis-city",
        "credit": 0,
        "district": "",
        "image_count": 7,
        "price": 2700000000,
        "rent": 0,
        "token": "gZmjfwwY"
    },
    "sc_time": 1728471692.6513011
}