{
    "Id": "f7389f5c-19de-42cd-a071-cc56af110018",
    "AdverTypeValue": 1,
    "AdverTypeTitle": "رهن و اجاره",
    "EstateTypeValue": 1,
    "EstateTypeTitle": "آپارتمان",
    "CityAreaId": "67e48807-902e-4a32-9f8d-9e0484f1d1dd",
    "CityAreaTitle": "پردیس",
    "CityAreaGroupTitle": null,
    "AreaSize": 87.0,
    "AreaSizeMin": null,
    "BedroomCount": 2,
    "Summary": "اجاره آپارتمان در فاز ۱۱ پردیس - آپارتمان ۸۷ متری، ۲ خواب\nفاز ۱۱، زون ۴ جنوبی، طبقه دوم\nپارکینگ سرباز و روبروی ساختمان به صورت شماره گذاری می باشد\nکاملا تمیز با همسایگان محترم و بدون سرو صدا\n- تعداد واحد در طبقه: ۴\n- وضعیت واحد: بازسازی نشده\n- جهت ساختمان: جنوبی\n- گرمایش:  شوفاژ\n- سرویس بهداشتی:  ایرانی و فرنگی\n- جنس کف:  سرامیک\nطبقه: ۲ از ۱۲\nامکانات: انباری, پارکینگ, آسانسور, بالکن",
    "VendorTypeTitle": "Divar",
    "VendorTypePersianTitle": "دیوار",
    "AnalysisDateTimeStr": "07/30/24 13:43:35",
    "AnalysisDateTime": "2024-07-30T13:43:35.047+03:30",
    "ExpressRemainedDay": 3,
    "Url": "https://redirect.melkradar.com/adver/dvr/gZoqqqKU?userType=realtor&clientId=721fb7039a7d412f99311146eb2ad3aa&adverId=gZoqqqKU",
    "ContactPhone": "09127108508",
    "RadarCode": "122311877",
    "SellTotalPrice": null,
    "RentMonthlyPrice": 2500000,
    "RentMortgagePrice": 250000000,
    "IsRequested": false,
    "PriceTypeStr": "",
    "IsActive": true,
    "BuiltDate": "7/30/2008 12:00:00 AM",
    "BuiltDateMin": "",
    "EstateTypeGroupTitle": "residential",
    "IsFoldered": false,
    "IsInDeafultFolder": false,
    "FolderTitle": null,
    "FolderId": null,
    "FolderDateTimeStr": null,
    "EstateTypeGroupValue": 1,
    "AdverTypeGroupValue": 1,
    "AreaSizeStr": "87 متر",
    "BuildDateStr": "۱۳۸۷",
    "CountOfRelatedCustomer": null,
    "CountOfRelatedNote": null,
    "Warehouse": 1,
    "Balcony": 1,
    "Elevator": 1,
    "Parking": 1,
    "OwnerFullName": null,
    "Address": null,
    "Description": null,
    "FolderItemId": null,
    "AgentAdverCreationType": null,
    "FilterAdverDateFromStr": null,
    "FilterAdverDateToStr": null,
    "FileCode": null,
    "IsRevived": null,
    "DeedType": null,
    "EstateType": "Apartment",
    "AdvertType": "Rent",
    "AdverDateTime": "2024-07-31T02:57:02Z",
    "AdverDate": null,
    "VendorType_Id": "8ce0bb2c-61bb-4884-9874-39b49d5d4d52",
    "EasyKey": null,
    "SellUnitPrice": null,
    "MelkId": "gZoqqqKU",
    "PriceType": null,
    "RealtorAnalyzeDateTime": "2024-07-30T10:13:35.047Z",
    "VendorImageUrls": [
        "https://s100.divarcdn.com/static/photo/neda/post/x8FES6kiAayCRL_zyRFPXw/45f14649-01e0-4535-b7bd-84966d901472.jpg"
    ],
    "ImageCount": 1,
    "CalculatedBuildingAge": 16,
    "BuildingAgeRanges": [],
    "RealtorAdverReports": [],
    "AdverKind": {
        "AdverCategory": "UsualAdver",
        "AdverButtons": []
    },
    "AdverImageUrls": [
        {
            "VendorImageUrl": "https://s100.divarcdn.com/static/photo/neda/post/x8FES6kiAayCRL_zyRFPXw/45f14649-01e0-4535-b7bd-84966d901472.jpg",
            "MelkRadarImageUrl": "https://mlkstoragelive.blob.core.windows.net/vendor-image-divar/f7389f5c-19de-42cd-a071-cc56af110018_1.jpg"
        }
    ]
}