{
    "seo": {
        "title": "فروش آپارتمان 133 متر در پونک - شیپور",
        "description": "طبقه ملک: 9 نمای ساختمان: سنگی آشپزخانه: نیمه فرنیش، اپن، نورگیر سقفی، سینک دوقلو، گاز رومیزی، هود کابینت: های گلاس کفپوش: سرامیک سیستم گرمایشی و سرمایشی: ",
        "h1": "فروش آپارتمان 133 متر در پونک"
    },
    "main": {
        "type": "publicListingDetails",
        "id": "437948735",
        "title": "فروش آپارتمان 133 متر در پونک",
        "url": "https://www.sheypoor.com/v/فروش-آپارتمان-133-متر-در-پونک-437948735.html",
        "timePassedLabel": "لحظاتی پیش",
        "imageCount": 20,
        "videoCount": 0,
        "price": [
            {
                "label": null,
                "amount": 17955000000,
                "currency": "تومان"
            }
        ],
        "description": "طبقه ملک: 9\nنمای ساختمان: سنگی\nآشپزخانه: نیمه فرنیش، اپن، نورگیر سقفی، سینک دوقلو، گاز رومیزی، هود\nکابینت: های گلاس\nکفپوش: سرامیک\nسیستم گرمایشی و سرمایشی: موتورخانه مرکزی، داکت اسپلیت\nامکانات رفاهی و تفریحی: فضای سبز، آلاچیق، لابی، باربیکیو\nامکانات ورزشی: میز بیلیارد، سالن بدنسازی\nامکانات امنیتی: آیفون تصویری، دوربین مداربسته، درب ضد سرقت، پله اضطراری، مرکز مانیتورینگ، اعلام حریق، نگهبانی 24 ساعته، اطفاء حریق\nسایر امکانات: برق اضطراری، آنتن مرکزی، کمد دیواری، نورپردازی، سرویس بهداشتی ایرانی، لابی من، سرویس بهداشتی فرنگی، خواب مستر، آبنما، کاغذ دیواری\n\n️ بهترین موقعیت خرید بی واسطه و مستقیم از انبوه ساز مطرح کشور حاج رحیم قربانی ️\n\n   ️️️️فرصت بازدید از این پروژه را از دست ندهید ️️️️\n\n️133متر نوساز کلید نخورده\n️سه خواب استاندارد\n️2پارکینگ سندی\n️پلان بی نظیر با پنجره های قدی\n️تراس بزرگ قابل چیدمان\n️سند آماده انتقال\n \nمشاعات هتلینگ مجلل و مبله:\n◀️کتابخانه\n◀️سالن سینما و آمفی تئاتر \n◀️سالنgym\n◀️سالن بیلیارد\n◀️آلاچیق\n◀️مهد کودک\n◀️آسانسور نفربر و باربری\n◀️سالن اجتماعات و پارتی رووم\n◀️لابی من و تیم نگهبانی 24ساعته\n\n️دفتر فروش انحصاری ابنیه سازان مقاوم حاج رحیم قربانی ️\n200متر پایین تر از میدان پونک بر اشرفی اصفهانی نبش غروی پارک اداری رونیکاپالاس طبقه اول واحد فروش \n\n️ جهت کسب اطلاعات بیشتر تماس حاصل فرمائید.\nکارشناس فروش:خانم جاوید⬅️(داخلی 133)️<br><span class=\"blue link  dir-ltr\">0992XXX1712(نمایش کامل)</span>",
        "location": {
            "longitude": 51.329813,
            "latitude": 35.765557
        },
        "videos": [],
        "IMAGE": [
            "https://cdn.sheypoor.com/imgs/2024/03/07/437948735/666x416_Sw/437948735_3d5e05d2cd02e66a38e4bb5531b12f30.webp",
            "https://cdn.sheypoor.com/imgs/2024/03/07/437948735/666x416_Sw/437948735_62d12eebb93e8b4b03c4bc52e046863f.webp",
            "https://cdn.sheypoor.com/imgs/2024/03/07/437948735/666x416_Sw/437948735_828d8c850820a5fed1de22fed9d5a6c3.webp",
            "https://cdn.sheypoor.com/imgs/2024/03/07/437948735/666x416_Sw/437948735_ba1a39c2e65de550de18a0b504db19dc.webp",
            "https://cdn.sheypoor.com/imgs/2024/03/07/437948735/666x416_Sw/437948735_b5c325bebdc9d305aa7c5aba8cb6d70a.webp",
            "https://cdn.sheypoor.com/imgs/2024/03/07/437948735/666x416_Sw/437948735_f6927c71e488e17e7a0b2878f4f8aae5.webp",
            "https://cdn.sheypoor.com/imgs/2024/03/07/437948735/666x416_Sw/437948735_0bd207c12def3765ad3bf029b358fc89.webp",
            "https://cdn.sheypoor.com/imgs/2024/03/07/437948735/666x416_Sw/437948735_6cb4a49d05e541f011e2ac8167e29ca4.webp",
            "https://cdn.sheypoor.com/imgs/2024/03/07/437948735/666x416_Sw/437948735_b6e1bfedf8b46749933d3e4dd8837b0b.webp",
            "https://cdn.sheypoor.com/imgs/2024/03/07/437948735/666x416_Sw/437948735_e3a07d2db913b55ee94aefa700eb6d3f.webp",
            "https://cdn.sheypoor.com/imgs/2024/03/07/437948735/666x416_Sw/437948735_ebca1037ea6bf86768deb587461b69f9.webp",
            "https://cdn.sheypoor.com/imgs/2024/03/07/437948735/666x416_Sw/437948735_aa4c72417dfde43cf35ae99e22901009.webp",
            "https://cdn.sheypoor.com/imgs/2024/03/07/437948735/666x416_Sw/437948735_1abbd220b9641e195ef2b5374756578a.webp",
            "https://cdn.sheypoor.com/imgs/2024/03/07/437948735/666x416_Sw/437948735_83ddc8cc75adc2c4a3db070f427386f5.webp",
            "https://cdn.sheypoor.com/imgs/2024/03/07/437948735/666x416_Sw/437948735_b7fea1341894e90c78b63047b677d5be.webp",
            "https://cdn.sheypoor.com/imgs/2024/03/07/437948735/666x416_Sw/437948735_3fd3f185c7849effffa4bb2b0fd33299.webp",
            "https://cdn.sheypoor.com/imgs/2024/03/07/437948735/666x416_Sw/437948735_776b1699351b0c71f5bb486e8b5eb200.webp",
            "https://cdn.sheypoor.com/imgs/2024/03/07/437948735/666x416_Sw/437948735_c3ccaea88e851088193b37fc0a13b7e4.webp",
            "https://cdn.sheypoor.com/imgs/2024/03/07/437948735/666x416_Sw/437948735_94d03e33c089667544d069c0bde52fe9.webp",
            "https://cdn.sheypoor.com/imgs/2024/03/07/437948735/666x416_Sw/437948735_db0ef5b412bb0e0017b6b397c23400e7.webp"
        ],
        "property": [
            {
                "متراژ": "133"
            },
            {
                "نوع ملک": "آپارتمان"
            },
            {
                "تعداد اتاق": "3"
            },
            {
                "پارکینگ": "دارد"
            },
            {
                "انباری": "دارد"
            },
            {
                "آسانسور": "دارد"
            },
            {
                "سن بنا": "1 سال"
            },
            {
                "قیمت هر متر": "135,000,000"
            }
        ],
        "category": [
            {
                "region": "استان تهران"
            },
            {
                "city": "تهران"
            },
            {
                "category_1": "املاک"
            },
            {
                "category_2": "خرید و فروش خانه و آپارتمان"
            },
            {
                "neighbourhood": "پونک"
            }
        ]
    },
    "sell_box": {
        "seller": {
            "url": "abniyesazanmoghavemghorbani",
            "name": "ابنیه سازان مقاوم قربانی",
            "registeredAt": "عضو شیپور از مرداد ۱۴۰۳",
            "image": "https://www.sheypoor.com/image/75cd4e/500x0_S/shop_photos/79167/Image.webp?1700379701",
            "rates": null,
            "hasReviews": false,
            "callbackUrl": null,
            "listingCount": null,
            "invoiceCount": null
        },
        "consultant": {
            "id": "171081",
            "name": "جاوید",
            "slug": "09923331712",
            "image": "https://www.sheypoor.com/image/30b901/110x110_af/users/5431/54314070_profile.jpg?1723645895",
            "registered_at": "2024-02-28 16:19:37",
            "user_id": "54314070",
            "isPremium": false,
            "categoryName": "املاک",
            "locationsRegions": "تهران",
            "rate": null,
            "registeredAtTimestamp": 1709124577,
            "shopName": "ابنیه سازان مقاوم قربانی",
            "registerDate": "عضو شیپور از اسفند ۱۴۰۲",
            "countListings": 62,
            "link": "https://www.sheypoor.com/users/zLZ1N7"
        }
    }
}